graph_snapshot/__init__.py
graph_snapshot/graph_snapshot.py
graph_snapshot-0.1.0.dist-info/LICENSE
graph_snapshot-0.1.0.dist-info/METADATA
graph_snapshot-0.1.0.dist-info/WHEEL
graph_snapshot-0.1.0.dist-info/top_level.txt
graph_snapshot-0.1.0.dist-info/RECORD
