Metadata-Version: 2.1
Name: graph-snapshot
Version: 0.1.0
Summary: A small package for creating snapshots of graphs with networkx
Home-page: https://josuakugler.github.io/graph_snapshot/
Author: Josua Kugler, Nico Haaf
Author-email: josua.kugler@stud.uni-heidelberg.de, nico.haaf@stud.uni-heidelberg.de
License: UNKNOWN
Platform: UNKNOWN
Classifier: Programming Language :: Python :: 3
Classifier: Operating System :: POSIX :: Linux
Requires-Python: >=3.8
